glomos/__init__.py
glomos/heuristic_ga.py
glomos/heuristic_ga_rotamers.py
glomos/libcalc_ani.py
glomos/libtools.py
glomos-0.1.5.dist-info/licenses/LICENSE
glomos-0.1.5.dist-info/METADATA
glomos-0.1.5.dist-info/WHEEL
glomos-0.1.5.dist-info/top_level.txt
glomos-0.1.5.dist-info/RECORD
