Metadata-Version: 2.4
Name: glomos
Version: 0.1.5
Summary: GLobal Optimization of MOlecular Systems
Author-email: Filiberto Ortiz Chi <fortiz666@gmail.com>
License: MIT
Project-URL: Homepage, https://github.com/fortizchi/glomos
License-File: LICENSE
Requires-Dist: ase
Requires-Dist: torchani
Requires-Dist: aegon==1.2.5
Dynamic: license-file
